datavalue/__init__.py
datavalue/classes/__init__.py
datavalue/classes/primitive_data.py
datavalue/exceptions/__init__.py
tests/test.py
datavalue-0.1.5.dist-info/METADATA
datavalue-0.1.5.dist-info/WHEEL
datavalue-0.1.5.dist-info/top_level.txt
datavalue-0.1.5.dist-info/RECORD
