Metadata-Version: 2.4
Name: datavalue
Version: 0.1.5
Summary: Librería de tipos de datos primitivos y complejos
Author: Specter
Requires-Python: >=3.10
